setup.py
reeprovenance/__init__.py
reeprovenance/reeprovenance.py
reeprovenance.egg-info/PKG-INFO
reeprovenance.egg-info/SOURCES.txt
reeprovenance.egg-info/dependency_links.txt
reeprovenance.egg-info/requires.txt
reeprovenance.egg-info/top_level.txt